{"javascript_array_arraymethod.md":"a7b2bab0","css_center_center.md":"b2d15a35","css_color_color.md":"bba87032","css_flex_flex.md":"05895579","css_relayout_relayout.md":"ffd84fb5","designpatterns_observer_observer.md":"745cbca4","designpatterns_proxy.md":"bfdec79d","designpatterns_strategies_strategies.md":"7c2b7658","english_call_stack.md":"8ef1fd82","english_event.md":"08d53f30","english_event_loop.md":"8fe94039","english_excution_context.md":"40552d78","english_grammer.md":"90e02087","english_index.md":"e9141b8c","index.md":"8e1ae0a0","javascript_array_arrayfor.md":"2c974aaa","css_layout_layout.md":"eb976d30","css_selector_selector.md":"720eef40","designpatterns_singleton_singleton.md":"2d956bf2","css_bfc_bfc.md":"86e2d463","css_textoverflow_textoverflow.md":"9afefecc","designpatterns_iterator.md":"8efdefd4","javascript_closure.md":"7a72b1f1","javascript_copy.md":"6dc03e6d","javascript_data_type.md":"d9673d4c","javascript_debounce_debounce.md":"79d44830","javascript_equal.md":"07bb4909","javascript_event_event.md":"d75d31eb","javascript_event_loop_event_loop.md":"196549b0","javascript_execution_context_execution_context.md":"0d240bb6","javascript_generator.md":"ed53b4d1","javascript_iteration_iteration.md":"a18fa18b","javascript_object_createobj.md":"c712e6c3","javascript_class.md":"e572ad65","javascript_object_objectfor.md":"86917407","javascript_operator_precedence_operator_precedence.md":"0009b407","javascript_promise_promise.md":"0d6abbce","javascript_prototype.md":"6f4553a5","javascript_proxy_proxy.md":"6bf5f951","javascript_reflect_reflect.md":"5d5a31b2","javascript_scope.md":"9efccf24","javascript_string.md":"ce6554da","javascript_this_this.md":"ce59fd8c","javascript_throttle_throttle.md":"69e0c0cd","javascript_type_convert.md":"2bd81d25","javascript_typeof_typeof.md":"b5d21c27","other_git.md":"b0a633e2","other_npm.md":"80eb7243","other_ssh.md":"2883fde0","react_create.md":"bdc97b83","react_demo.md":"7ba3f62e","web_browser_browser.md":"3d6b9dfc","web_performance_performance.md":"c84deb73","javascript_higherorderfunction_higherorderfunction.md":"236c4887","javascript_iteration_iteration2.md":"4d174922","javascript_inherit.md":"3edb8189"}
